selenium_stealth_utils/__init__.py
selenium_stealth_utils/cloudflare_tools.py
selenium_stealth_utils/stealth_helper.py
selenium_stealth_utils/webdriver_utils.py
selenium_stealth_utils-2.0.0.dist-info/LICENSE
selenium_stealth_utils-2.0.0.dist-info/METADATA
selenium_stealth_utils-2.0.0.dist-info/WHEEL
selenium_stealth_utils-2.0.0.dist-info/top_level.txt
selenium_stealth_utils-2.0.0.dist-info/RECORD
