Metadata-Version: 2.1
Name: selenium-stealth-utils
Version: 2.0.0
Summary: Advanced web automation utilities with enhanced browser security and network protection features
Home-page: https://github.com/advanced-webtools/selenium-stealth-utils
Author: Advanced Web Tools
Author-email: advanced.webtools@example.com
License: UNKNOWN
Project-URL: Bug Reports, https://github.com/advanced-webtools/selenium-stealth-utils/issues
Project-URL: Source, https://github.com/advanced-webtools/selenium-stealth-utils
Project-URL: Documentation, https://github.com/advanced-webtools/selenium-stealth-utils#readme
Keywords: selenium,automation,browser,security,network,webdriver,testing
Platform: UNKNOWN
Classifier: Development Status :: 4 - Beta
Classifier: Intended Audience :: Developers
Classifier: License :: OSI Approved :: MIT License
Classifier: Operating System :: OS Independent
Classifier: Programming Language :: Python :: 3
Classifier: Programming Language :: Python :: 3.7
Classifier: Programming Language :: Python :: 3.8
Classifier: Programming Language :: Python :: 3.9
Classifier: Programming Language :: Python :: 3.10
Classifier: Programming Language :: Python :: 3.11
Classifier: Topic :: Software Development :: Libraries :: Python Modules
Classifier: Topic :: Internet :: WWW/HTTP :: Browsers
Classifier: Topic :: Security
Requires-Python: >=3.7
License-File: LICENSE
Requires-Dist: selenium>=4.0.0
Requires-Dist: selenium-stealth>=1.0.0
Requires-Dist: requests>=2.25.0
Requires-Dist: colorama>=0.4.4
Requires-Dist: beautifulsoup4>=4.9.0
Requires-Dist: psutil>=5.8.0
